aiosupermicro/__init__.py
aiosupermicro/auth.py
aiosupermicro/client.py
aiosupermicro/const.py
aiosupermicro/exceptions.py
aiosupermicro/py.typed
aiosupermicro/models/__init__.py
aiosupermicro/models/accounts.py
aiosupermicro/models/base.py
aiosupermicro/models/chassis.py
aiosupermicro/models/common.py
aiosupermicro/models/enums.py
aiosupermicro/models/events.py
aiosupermicro/models/logs.py
aiosupermicro/models/manager.py
aiosupermicro/models/oem.py
aiosupermicro/models/power.py
aiosupermicro/models/sessions.py
aiosupermicro/models/system.py
aiosupermicro/models/thermal.py
aiosupermicro/models/update.py
supermicro_redfish_client-1.1.0.dist-info/licenses/LICENSE
supermicro_redfish_client-1.1.0.dist-info/METADATA
supermicro_redfish_client-1.1.0.dist-info/WHEEL
supermicro_redfish_client-1.1.0.dist-info/top_level.txt
supermicro_redfish_client-1.1.0.dist-info/RECORD
