Metadata-Version: 2.4
Name: supermicro-redfish-client
Version: 1.1.0
Summary: Async Python client for Supermicro Redfish BMC API
Author-email: Deroy2112 <81692934+Deroy2112@users.noreply.github.com>
License: MIT
Project-URL: Homepage, https://github.com/Deroy2112/supermicro-redfish-client
Project-URL: Bug Tracker, https://github.com/Deroy2112/supermicro-redfish-client/issues
Project-URL: Documentation, https://github.com/Deroy2112/supermicro-redfish-client#readme
Keywords: supermicro,redfish,bmc,ipmi,async,aiohttp,home-assistant
Classifier: Development Status :: 4 - Beta
Classifier: Intended Audience :: Developers
Classifier: License :: OSI Approved :: MIT License
Classifier: Operating System :: OS Independent
Classifier: Programming Language :: Python :: 3
Classifier: Programming Language :: Python :: 3.11
Classifier: Programming Language :: Python :: 3.12
Classifier: Programming Language :: Python :: 3.13
Classifier: Topic :: Home Automation
Classifier: Topic :: System :: Hardware
Classifier: Topic :: System :: Monitoring
Classifier: Typing :: Typed
Classifier: Framework :: AsyncIO
Requires-Python: >=3.11
License-File: LICENSE
Requires-Dist: aiohttp>=3.8.0
Provides-Extra: dev
Requires-Dist: pytest>=7.0; extra == "dev"
Requires-Dist: pytest-asyncio>=0.21; extra == "dev"
Requires-Dist: pytest-cov>=4.0; extra == "dev"
Requires-Dist: aioresponses>=0.7; extra == "dev"
Requires-Dist: mypy>=1.0; extra == "dev"
Requires-Dist: ruff>=0.1; extra == "dev"
Dynamic: license-file
